{

    "tabledef": 
            {
                "language": "lv",
                "lengthChange": "false", 
                "pageLength":"10",
                "autoWidth": "false"
            },

    "columns": [
         {
            "title": "Pievienoja", 
            "slug": "pievienoja",
            "columnDefs": 
                    {
                        "className": "text-start"                          
                    }
        },
        
        {
            "title": "Datums un laiks", 
            "slug": "datums-un-laiks",
            "columnDefs": 
                    {
                        "className": "text-start"                          
                    }
        },
         {
            "title": "Komentārs", 
            "slug": "komentars",
            "columnDefs": 
                    {
                        "className": "text-start"                          
                    }
        },
        
        {
            "title": "Datne", 
            "slug": "datne",
            "columnDefs": 
                    {
                        "className": "text-start"                          
                    }
        }
    ]
}